lockey/__init__.py
lockey/clear_clipboard.sh
lockey/main.py
lockey-0.3.4.dist-info/LICENSE
lockey-0.3.4.dist-info/METADATA
lockey-0.3.4.dist-info/WHEEL
lockey-0.3.4.dist-info/entry_points.txt
lockey-0.3.4.dist-info/RECORD
