Metadata-Version: 2.1
Name: lockey
Version: 0.3.4
Summary: 
Author: NikolaiLyssogor
Author-email: lyssogor@gmail.com
Requires-Python: >=3.12,<4.0
Classifier: Programming Language :: Python :: 3
Classifier: Programming Language :: Python :: 3.12
